<?xml version="1.0" encoding="UTF-8"?>
<configuration>
    <property name="LOG_PATH" value="./logs" />
    <property name="LOG_FILE_NAME" value="exbuilder6-ai-server" />

    <!-- Console Appender -->
    <appender name="CONSOLE" class="ch.qos.logback.core.ConsoleAppender">
        <encoder>
            <pattern>%d{yyyy-MM-dd HH:mm:ss.SSS} [%thread] %highlight(%-5level) %cyan(%logger{36}) - %msg%n</pattern>
        </encoder>
    </appender>

    <!-- Rolling File Appender -->
    <appender name="FILE" class="ch.qos.logback.core.rolling.RollingFileAppender">
        <file>${LOG_PATH}/${LOG_FILE_NAME}.log</file>
        <encoder>
            <pattern>%d{yyyy-MM-dd HH:mm:ss.SSS} [%thread] %-5level %logger{36} - %msg%n</pattern>
        </encoder>
        <rollingPolicy class="ch.qos.logback.core.rolling.SizeAndTimeBasedRollingPolicy">
            <fileNamePattern>${LOG_PATH}/archived/${LOG_FILE_NAME}.%d{yyyy-MM-dd}.%i.log</fileNamePattern>
            <maxFileSize>10MB</maxFileSize>
            <maxHistory>30</maxHistory>
            <totalSizeCap>1GB</totalSizeCap>
        </rollingPolicy>
    </appender>

    <!-- Application Log Level -->
    <logger name="com.example.ai" level="DEBUG" />
    
    <!-- Spring Log Level -->
    <logger name="org.springframework" level="INFO" />

    <!-- Root Level -->
    <root level="DEBUG">
        <appender-ref ref="CONSOLE" />
        <appender-ref ref="FILE" />
    </root>
</configuration>
